pyodim/__init__.py
pyodim/__version__.py
pyodim/pyodim.py
pyodim-0.5.8.dist-info/licenses/LICENSE
pyodim-0.5.8.dist-info/METADATA
pyodim-0.5.8.dist-info/WHEEL
pyodim-0.5.8.dist-info/top_level.txt
pyodim-0.5.8.dist-info/RECORD
