Metadata-Version: 2.4
Name: pyodim
Version: 0.5.8
Summary: An Odim hdf5 file reader.
Author-email: Valentin Louf <valentin.louf@bom.gov.au>
Maintainer-email: Valentin Louf <valentin.louf@bom.gov.au>
License: MIT
Project-URL: Homepage, https://github.com/vlouf/pyodim
Project-URL: Repository, https://github.com/vlouf/pyodim
Keywords: odim,h5,radar,file,reader
Classifier: Development Status :: 5 - Production/Stable
Classifier: Intended Audience :: Science/Research
Classifier: Topic :: Scientific/Engineering :: Atmospheric Science
Classifier: License :: OSI Approved :: MIT License
Classifier: Programming Language :: Python :: 3.8
Classifier: Programming Language :: Python :: 3.9
Classifier: Programming Language :: Python :: 3.10
Classifier: Programming Language :: Python :: 3.11
Classifier: Programming Language :: Python :: 3.12
Classifier: Programming Language :: Python :: 3.13
Classifier: Programming Language :: Python :: 3.14
Requires-Python: >=3.8
License-File: LICENSE
Requires-Dist: numpy>=1.21.0
Requires-Dist: dask>=2020.12.0
Requires-Dist: xarray>=0.18.0
Requires-Dist: pyproj>=3.1.0
Requires-Dist: h5py>=3.0
Provides-Extra: dev
Requires-Dist: pytest; extra == "dev"
Provides-Extra: test
Requires-Dist: pytest; extra == "test"
Dynamic: license-file
